islpy/__init__.py
islpy/_isl.cpython-312-aarch64-linux-gnu.so
islpy/_isl.pyi
islpy/_monkeypatch.py
islpy/py.typed
islpy/version.py
islpy_barvinok.libs/libbarvinok-df68b022.so.23.0.13
islpy_barvinok.libs/libgmp-c0624462.so.10.5.0
islpy_barvinok.libs/libisl-50a6c98f.so.23.4.0
islpy_barvinok.libs/libntl-7fac2127.so.35.0.0
islpy_barvinok.libs/libpolylibgmp-12fd8754.so.8.2.0
islpy_barvinok-2025.2.5.dist-info/METADATA
islpy_barvinok-2025.2.5.dist-info/WHEEL
islpy_barvinok-2025.2.5.dist-info/RECORD
