Metadata-Version: 2.4
Name: islpy-barvinok
Version: 2025.2.5
Summary: Wrapper around isl, an integer set library
Author-Email: Andreas Kloeckner <inform@tiker.net>
License-Expression: MIT
Classifier: Development Status :: 4 - Beta
Classifier: Intended Audience :: Developers
Classifier: Intended Audience :: Other Audience
Classifier: Intended Audience :: Science/Research
Classifier: Programming Language :: C++
Classifier: Programming Language :: Python
Classifier: Programming Language :: Python :: 3
Classifier: Topic :: Scientific/Engineering
Classifier: Topic :: Scientific/Engineering :: Mathematics
Classifier: Topic :: Scientific/Engineering :: Physics
Classifier: Topic :: Scientific/Engineering :: Visualization
Classifier: Topic :: Software Development :: Libraries
Project-URL: Documentation, https://documen.tician.de/islpy
Project-URL: Repository, https://github.com/inducer/islpy
Requires-Python: <3.14,>=3.10
